flask_vue/__init__.py
flask_vue/cli.py
flask_vue/config.py
flask_vue/extension.py
flask_vue/plugins.py
flask_vue3-0.1.1.dist-info/licenses/LICENSE
flask_vue3-0.1.1.dist-info/METADATA
flask_vue3-0.1.1.dist-info/WHEEL
flask_vue3-0.1.1.dist-info/top_level.txt
flask_vue3-0.1.1.dist-info/RECORD
